{"parcel_and_couriers":[{"website":"patelparcelservices.com ","address":"Peepal Wali 6456\/A, Katra Bariyan Fatehpuri, Chandni Chowk New Delhi, Delhi 110006.","reviewsLink":"https:\/\/www.google.com\/search?q=Patel+Parcel,+Peepal+Wali,+6456\/A,+Katra+Bariyan,+Fatehpuri,+Chandni+Chowk,+New+Delhi,+Delhi+110006&amp;ludocid=13520506168737953135#lrd=0x390cfd1236703695:0xbba27cb9cb1a756f,1","reviews":"1 ","img_url":"https:\/\/www.google.com\/earth\/rpc\/images\/cleardot.gif","latitude":"77.221959","name":" Patel Parcel","rating":"5.0","phno":"011 2398 2609 ","longitude":"28.655738"},{"website":"epspl.net ","address":"328 Sant Nagar, East of Kailash New Delhi, Delhi 110065.","reviewsLink":"https:\/\/www.google.com\/search?q=Express+Parcel+Services+Pvt.+Ltd.,+328,+Sant+Nagar,+East+of+Kailash,+New+Delhi,+Delhi+110065&amp;ludocid=14915599705306423319#lrd=0x390ce3c85d76ae87:0xcefedae7deb5e017,1","reviews":"1 ","img_url":"https:\/\/www.google.com\/earth\/rpc\/images\/cleardot.gif","latitude":"77.2505259","name":" Express Parcel Services Pvt. Ltd.","rating":"5.0","phno":"011 4567 9999 ","longitude":"28.5553672"},{"website":"parcel.indianrail.gov.in ","address":"RAILWAY BOARD Block E, North West Moti Bagh New Delhi, Delhi 110001.","reviewsLink":"https:\/\/www.google.com\/search?q=Railway+Parcel+Service,+RAILWAY+BOARD,+Block+E,+North+West+Moti+Bagh,+New+Delhi,+Delhi+110001&amp;ludocid=669370778092446656#lrd=0x390d1d7031155555:0x94a152d1b3a23c0,1","reviews":"21 ","img_url":"https:\/\/www.google.com\/earth\/rpc\/images\/cleardot.gif","latitude":"77.1805983","name":" Railway Parcel Service","rating":"1.5","phno":"011 2330 3850 ","longitude":"28.584458"},{"website":" ","address":"Shop No-T-298, General Market, Main Bazar, Opposite Ajay Guest House Main Bazar Rd Aram Bagh, Bharat Nagar, Paharganj New Delhi, Delhi 110055.","reviewsLink":"#","reviews":"null","img_url":"https:\/\/lh5.googleusercontent.com\/-B7aw6vfTrK0\/VSjNsHKwf4I\/AAAAAAAAAA8\/nZYOtUtW6O8iDZPHdasZxi5LAkrVocjvwCJkC\/w408-h407-k-no\/","latitude":"77.21178399999999","name":" Sanjay Parcel Packing Service","rating":"null","phno":"011 2358 5682 ","longitude":"28.640757"},{"website":" ","address":"2465\/10, 3rd Floor Gurudwara Rd Block 35M, Beadonpura, Karol Bagh New Delhi, Delhi 110005.","reviewsLink":"#","reviews":"null","img_url":"https:\/\/www.google.com\/earth\/rpc\/images\/cleardot.gif","latitude":"77.19284019999999","name":" Sri Sai Parcel Service","rating":"null","phno":"074282 50202 ","longitude":"28.6501611"},{"website":" ","address":"Shop No.63, J.D. Chamber, Mazinine Floor Swami Shradhanand Marg Chabdi Bazar, Farash Khana, Chandni Chowk New Delhi, Delhi 110006.","reviewsLink":"https:\/\/www.google.com\/search?q=Nav+Bharat+Parcel+Services,+Shop+No.63,+J.D.+Chamber,+Mazinine+Floor,+Swami+Shradhanand+Marg,+Chabdi+Bazar,+Farash+Khana,+Chandni+Chowk,+New+Delhi,+Delhi+110006&amp;ludocid=9913546761825712052#lrd=0x390cfd145ba6b1ff:0x8993fe4172d877b4,1","reviews":"1 ","img_url":"https:\/\/www.google.com\/earth\/rpc\/images\/cleardot.gif","latitude":"77.219326","name":" Nav Bharat Parcel Services","rating":"1.0","phno":"093125 66841 ","longitude":"28.652835"},{"website":"epspl.net ","address":"A 27 A, Mayapuri Industrial Area opposite lane New Era Public School, Mayapuri Industrial Phase 2nd Rd Sangam Vihar, Mayapuri Industrial Area Phase II, Mayapuri New Delhi, Delhi 110064.","reviewsLink":"https:\/\/www.google.com\/search?q=Express+Parcel+Services+Pvt.+Ltd,+A+27+A,+Mayapuri+Industrial+Area,+opposite+lane+New+Era+Public+School,+Mayapuri+Industrial+Phase+2nd+Rd,+Sangam+Vihar,+Mayapuri+Industrial+Area+Phase+II,+Mayapuri,+New+Delhi,+Delhi+110064&amp;ludocid=13574779530449370663#lrd=0x390d034dba66be93:0xbc634e0f88adbe27,1","reviews":"2 ","img_url":"https:\/\/www.google.com\/earth\/rpc\/images\/cleardot.gif","latitude":"77.1160841","name":" Express Parcel Services Pvt. Ltd","rating":"5.0","phno":"011 4567 9999 ","longitude":"28.6174528"},{"website":" ","address":"84, Lal Singh Building, Main Vasantkunj Road Mahipalpur Extension Pocket 8, Sector C, Vasant Kunj New Delhi, Delhi 110037.","reviewsLink":"#","reviews":"null","img_url":"https:\/\/www.google.com\/earth\/rpc\/images\/cleardot.gif","latitude":"77.140607","name":" United Parcel Express","rating":"null","phno":"011 5168 7688 ","longitude":"28.5360587"},{"website":"globalparcelservices.in ","address":"207, Vats market, near madhuban chowk Shiva Market, Harsh Vihar, Pitampura Delhi, 110034.","reviewsLink":"#","reviews":"null","img_url":"https:\/\/www.google.com\/earth\/rpc\/images\/cleardot.gif","latitude":"77.13030999999999","name":" Global Parcel Services","rating":"null","phno":"098114 11015 ","longitude":"28.701214"},{"website":"parcel.indianrail.gov.in ","address":"Ajmeri Gate New Delhi, Delhi 110002.","reviewsLink":"https:\/\/www.google.com\/search?q=New+Delhi+Railway+Station+Parcel+Office,+Ajmeri+Gate,+New+Delhi,+Delhi+110002&amp;ludocid=2166031736595552416#lrd=0x390cfd3e5cb0ef59:0x1e0f4a63680018a0,1","reviews":"8 ","img_url":"https:\/\/lh5.googleusercontent.com\/-LA3tiF1QmyI\/WJEyn9dHH1I\/AAAAAAAA0-Y\/sifieInc0-0XYC-OK8onrNOma3MnRAYdwCLIB\/w408-h306-k-no\/","latitude":"77.2215346","name":" New Delhi Railway Station Parcel Office","rating":"2.5","phno":"079060 51316 ","longitude":"28.644512"},{"website":" ","address":"248 Kamla Market, Kamla Market, Ajmeri Gate Delhi, 110002.","reviewsLink":"https:\/\/www.google.com\/search?q=Okara+Parcel+Service,+248,+Kamla+Market,,+Kamla+Market,+Ajmeri+Gate,+Delhi,+110002&amp;ludocid=2304296015218285536#lrd=0x390cfd3db98ac3c7:0x1ffa8104646f1be0,1","reviews":"1 ","img_url":"http:\/\/www.google.com\/earth\/rpc\/images\/cleardot.gif","latitude":"77.22495499999999","name":" Okara Parcel Service","rating":"5.0","phno":"093122 66123 ","longitude":"28.64503"},{"website":" ","address":"1325-B, Behind Bata Showroom Kashmere Gate New Delhi, Delhi 110006.","reviewsLink":"https:\/\/www.google.com\/search?q=Sakti+Rail+Parcel+Service,+1325-B,+Behind+Bata+Showroom,+Kashmere+Gate,+New+Delhi,+Delhi+110006&amp;ludocid=4998610030165750976#lrd=0x390cfd061eec6095:0x455ea156b2bbf4c0,1","reviews":"1 ","img_url":"http:\/\/www.google.com\/earth\/rpc\/images\/cleardot.gif","latitude":"77.22926099999999","name":" Sakti Rail Parcel Service","rating":"1.0","phno":"093126 58673 ","longitude":"28.665813"},{"website":"flymyparcel.com ","address":"L-77\/187, Gali N.L.7 Mahipalpur Extn. Block F, Mahipalpur Village, Mahipalpur New Delhi, Delhi 110037.","reviewsLink":"#","reviews":"null","img_url":"http:\/\/lh3.googleusercontent.com\/proxy\/6NbOhpYAVovXt4HQUG1FMT66UlXWfftkxc7VVgNmF6Sx_FKeB9LRvzQ8mm_k0Kj-SYmEFTWTpqlDtdg58F5Sn90a4rpvdmdCTlJHlVOE6JTCwF1ADDlRKxAZk47SC2LYMtZN88jVQ48XpuMqpG4-M9h_1Q=w408-h306-k-no","latitude":"77.1239289","name":" Fly My Parcel","rating":"null","phno":"098733 89914 ","longitude":"28.544864"},{"website":" ","address":"Shop No.900, Near Hotel Namaskar, Main Bazar Kumaharan Gali Aram Bagh, Sidarth Basti, Aram Bagh, Paharganj New Delhi, Delhi 110055.","reviewsLink":"#","reviews":"null","img_url":"http:\/\/lh5.googleusercontent.com\/-R7Hd43eXwqU\/VLpVXWK4IfI\/AAAAAAAAABE\/Gl6o1KJGP2MtF6NLcbFmap5Z6US5VDNtQCJkC\/w408-h408-k-no\/","latitude":"77.214281","name":" Rainbow Exports India","rating":"null","phno":"098103 34263 ","longitude":"28.641793"},{"website":" ","address":"D-67\/1 Laxmi Market Sushant Lok Phase 1, Minto Bridge Colony, Barakhamba New Delhi, Delhi 110067.","reviewsLink":"#","reviews":"null","img_url":"http:\/\/www.google.com\/earth\/rpc\/images\/cleardot.gif","latitude":"77.22496629999999","name":" Ace Parcel Services Pvt Ltd","rating":"null","phno":"098111 70188 ","longitude":"28.6353228"},{"website":" ","address":"AG-41 Block AG, Sanjay Gandhi Transport Nagar Delhi, 110042.","reviewsLink":"#","reviews":"null","img_url":"http:\/\/www.google.com\/earth\/rpc\/images\/cleardot.gif","latitude":"77.151505","name":" Okara Parcel Services","rating":"null","phno":"011 3262 2091 ","longitude":"28.736632"},{"website":"epspl.net ","address":"-2 A 27A Mayapuri Industrial Area Phase II, Mayapuri New Delhi, Delhi 110064.","reviewsLink":"#","reviews":"null","img_url":"http:\/\/www.google.com\/earth\/rpc\/images\/cleardot.gif","latitude":"77.1197602","name":" Express Parcel Service Pvt. Ltd","rating":"null","phno":"011 4567 9999 ","longitude":"28.6240081"},{"website":"shipturn.in ","address":"D-88, Nanhey Park, Matiala Extension, Uttam Nagar Delhi, 110059.","reviewsLink":"https:\/\/www.google.com\/search?q=ShipTurn+Parcel+Services,+D-88,,+Nanhey+Park,+Matiala+Extension,+Uttam+Nagar,+Delhi,+110059&amp;ludocid=3339724600392986691#lrd=0x390d052ea9bcdb29:0x2e5915d4560eb043,1","reviews":"2 ","img_url":"http:\/\/lh4.googleusercontent.com\/-P6YWuWtlxl4\/V32qv5Cm0RI\/AAAAAAAAAyg\/ChuNNav1Ot4PgnihzudB30B5ymYNMSBOACLIB\/w408-h306-k-no\/","latitude":"77.05007599999999","name":" ShipTurn Parcel Services","rating":"5.0","phno":"090137 30107 ","longitude":"28.61085899999999"},{"website":"reliablesinternational.com ","address":"Kalka Devi Marg Block E, Amar Colony, Lajpat Nagar 4 New Delhi, Delhi 110024.","reviewsLink":"#","reviews":"null","img_url":"http:\/\/www.google.com\/earth\/rpc\/images\/cleardot.gif","latitude":"77.2412145","name":" RELIABLE PARCEL SERVICE","rating":"null","phno":"011 4100 3092 ","longitude":"28.5600593"},{"website":" ","address":"T-783 F Gali Number 3 Durga Mohalla, Block 4, Baljit Nagar, Patel Nagar New Delhi, Delhi 110008.","reviewsLink":"https:\/\/www.google.com\/search?q=Carry+Parcel,+T-783+F,+Gali+Number+3,+Durga+Mohalla,+Block+4,+Baljit+Nagar,+Patel+Nagar,+New+Delhi,+Delhi+110008&amp;ludocid=7768980180672667297#lrd=0x390d02f756760ec3:0x6bd0f650000b5ea1,1","reviews":"2 ","img_url":"http:\/\/www.google.com\/earth\/rpc\/images\/cleardot.gif","latitude":"77.1601342","name":" Carry Parcel","rating":"5.0","phno":"099718 81015 ","longitude":"28.6583857"},{"website":" ","address":"Shop No. T-138, General Market, Main Bazar, Opposite Khanna Cinema &amp; Vivek Hotel, Adjoining Yes Please Guest House Main Bazar Rd Aram Bagh, Sidarth Basti, Aram Bagh, Paharganj New Delhi, Delhi 110055.","reviewsLink":"#","reviews":"null","img_url":"http:\/\/www.google.com\/earth\/rpc\/images\/cleardot.gif","latitude":"77.212318","name":" Shiva Parcels","rating":"null","phno":"011 4358 4009 ","longitude":"28.640865"},{"website":" ","address":"198, Basement, Sant Nagar, East of Kailash Garhi, East of Kailash New Delhi, Delhi 110065.","reviewsLink":"#","reviews":"null","img_url":"http:\/\/www.google.com\/earth\/rpc\/images\/cleardot.gif","latitude":"77.25129179999999","name":" International Parcel Services","rating":"null","phno":"011 4132 6092 ","longitude":"28.55417749999999"},{"website":" ","address":"9803, NEAR WINE SHOP Gali Number 7 Multani Dhanda, Paharganj New Delhi, Delhi 110055.","reviewsLink":"https:\/\/www.google.com\/search?q=ARYA+PARCEL+SERVICE,+9803,+NEAR+WINE+SHOP,+Gali+Number+7,+Multani+Dhanda,+Paharganj,+New+Delhi,+Delhi+110055&amp;ludocid=14296058717969900647#lrd=0x390cfd6a191b62ab:0xc665cda904b8e467,1","reviews":"1 ","img_url":"http:\/\/lh6.googleusercontent.com\/-rvgbOs6mROI\/VWgnYA9roUI\/AAAAAAAAABI\/yMiCc-Z-bC0DPMOYs42pCqGIFVt8YXfuQCJkC\/w408-h412-k-no\/","latitude":"77.212259","name":" ARYA PARCEL SERVICE","rating":"5.0","phno":"099997 82167 ","longitude":"28.647045"},{"website":"pps.in ","address":"1, East Ave Punjabi Bagh East, Punjabi Bagh Cooperative Housing Soceity, East Punjabi Bagh, Punjabi Bagh New Delhi, Delhi 110026.","reviewsLink":"#","reviews":"null","img_url":"http:\/\/www.google.com\/earth\/rpc\/images\/cleardot.gif","latitude":"77.146231","name":" Prakash Parcel Services","rating":"null","phno":"011 4754 0001 ","longitude":"28.669607"},{"website":" ","address":"Regent Tower Ghaffar Market, Block 24N, Beadonpura, Karol Bagh New Delhi, Delhi 110005.","reviewsLink":"#","reviews":"null","img_url":"http:\/\/lh6.googleusercontent.com\/--QakpK06I9g\/ViXYQUUC8hI\/AAAAAAAAAAk\/ct4usK7-VSAlUQxieVpW-N6q-PjZZ007gCJkC\/w408-h408-k-no\/","latitude":"77.191141","name":" Khan Bhai Parcel Booking","rating":"null","phno":"098184 77121 ","longitude":"28.650672"},{"website":" ","address":"3495, Nicholson Rd Ram Bazar, South Indian Madrasi Colony, Mori Gate New Delhi, Delhi 110006.","reviewsLink":"#","reviews":"null","img_url":"http:\/\/www.google.com\/earth\/rpc\/images\/cleardot.gif","latitude":"77.22264299999999","name":" Bombay Express Parcel Service","rating":"null","phno":"null","longitude":"28.664677"},{"website":" ","address":"Kashmeri Near Chabbhi Delhi Chabi Ganj, Kashmere Gate New Delhi, Delhi 110006.","reviewsLink":"#","reviews":"null","img_url":"http:\/\/lh4.googleusercontent.com\/-Nk8QUwU1zEI\/Vo0Cpcm3IZI\/AAAAAAAAAAc\/2_tLJiyXP1gVvd2XmkY-ECmMyn89uWJIQCJkC\/w408-h406-k-no\/","latitude":"77.231534","name":" Daily Parcel Service","rating":"null","phno":"076896 58896 ","longitude":"28.663061"},{"website":" ","address":"64, G B Road, Behind khothi Mori Gate New Delhi, Delhi 110006.","reviewsLink":"#","reviews":"null","img_url":"http:\/\/lh3.googleusercontent.com\/-k99rJ0qfrkk\/VozgrILFajI\/AAAAAAAAAAc\/5eQZuH1WqSMw1iKZBgu9YNWk0v5q12Z_gCJkC\/w408-h406-k-no\/","latitude":"77.234588","name":" Daily Parcel Service","rating":"null","phno":"094150 43455 ","longitude":"28.661078"},{"website":" ","address":"Gali No. 23, Naiwala Behind Jain Mandir, Karoalbagh Block 18B, Dev Nagar, Karol Bagh New Delhi, Delhi 110005.","reviewsLink":"#","reviews":"null","img_url":"http:\/\/lh5.googleusercontent.com\/-2DzQWEScCCo\/VozgAFg4eII\/AAAAAAAAABA\/u9jkApsHEb4-6dmvmAdMCQBw7uGGm9JdACJkC\/w408-h406-k-no\/","latitude":"77.18746","name":" Daily Parcel Service","rating":"null","phno":"094150 43455 ","longitude":"28.655679"},{"website":" ","address":"11656\/1,Sat Nagar ,Near ICICI Bank Block 1, Regar Pura, Karol Bagh New Delhi, Delhi 110005.","reviewsLink":"#","reviews":"null","img_url":"http:\/\/lh3.googleusercontent.com\/-xD5hmIuR_bQ\/WPhSqtnZrrI\/AAAAAAAAABU\/D6IsI5JZei8wylwKIOdogPCvH1HHsLmCACLIBGAYYCw\/w544-h306-k-no\/","latitude":"77.18401299999999","name":" Daily Parcel Service","rating":"null","phno":"076781 61848 ","longitude":"28.649657"},{"website":" ","address":"H-70, Main road, zero pusta, Shastri park Kaithwara Jagjivan Nagar, New Usmanpur, Shahdara Delhi, 110053.","reviewsLink":"#","reviews":"null","img_url":"http:\/\/lh3.googleusercontent.com\/-DEVNup9m-js\/V80-6qLioNI\/AAAAAAAAAA8\/MJRUGknJD5A5ETc1PL015JQ0SVi_X4QIwCJkC\/w408-h408-k-no\/","latitude":"77.257696","name":" Aqsa Parcel Services","rating":"null","phno":"081307 66771 ","longitude":"28.678202"},{"website":" ","address":"Najafgarh Rd Block C, Najafgarh Road Industrial Area New Delhi, Delhi 110008.","reviewsLink":"#","reviews":"null","img_url":"http:\/\/www.google.com\/earth\/rpc\/images\/cleardot.gif","latitude":"77.15282499999999","name":" Ganpat Parcel Service","rating":"null","phno":"098181 83393 ","longitude":"28.662228"},{"website":"epickr.com ","address":"A-13, 1st floor, Pandav Nagar complex, Pandav Nagar Ganesh Nagar Tilak Nagar New Delhi, Delhi 110092.","reviewsLink":"https:\/\/www.google.com\/search?q=ePickr.com,+A-13,+1st+floor,+Pandav+Nagar+complex,+Pandav+Nagar,+Ganesh+Nagar,+Tilak+Nagar,+New+Delhi,+Delhi+110092&amp;ludocid=5285233133405382568#lrd=0x390d04965223cc91:0x4958eb884fc0a7a8,1","reviews":"1 ","img_url":"http:\/\/www.google.com\/earth\/rpc\/images\/cleardot.gif","latitude":"77.08777019999999","name":" ePickr.com","rating":"5.0","phno":"087438 31214 ","longitude":"28.6361183"},{"website":"couriergenie.com ","address":"Kendriya Vihar, Sector 56 Gurgaon, Haryana.","reviewsLink":"https:\/\/www.google.com\/search?q=Courier+Genie:+Courier+%26+Parcel+Delivery+Services,+Kendriya+Vihar,+Sector+56,+Gurgaon,+Haryana&amp;ludocid=7328119620435402333#lrd=0x390d1d838bec1ec1:0x65b2b5f7ff9f5e5d,1","reviews":"15 ","img_url":"http:\/\/lh4.googleusercontent.com\/-5_AskvzWm44\/V1EZbqUj4BI\/AAAAAAAAABQ\/CY-T7GzU_mQzwPt8kJBfWQivncCSQ0U9wCLIBGAYYCw\/w584-h306-k-no\/","latitude":"76.84622212776644","name":" Courier Genie: Courier Parcel Delivery Services","rating":"3.9","phno":"1800 3000 4243 ","longitude":"28.23998349582483"},{"website":"meratask.com ","address":"1004 10th Floor NDM-1 Netaji Subhash Place, Pitam Pura Netaji Subash Place, Shakurpur Delhi, 110034.","reviewsLink":"https:\/\/www.google.com\/search?q=Meratask,+1004+10th+Floor+NDM-1+Netaji+Subhash+Place,+Pitam+Pura,+Netaji+Subash+Place,+Shakurpur,+Delhi,+110034&amp;ludocid=3218248527744752444#lrd=0x390d02349a4bbf61:0x2ca983fc27265b3c,1","reviews":"7 ","img_url":"http:\/\/lh5.googleusercontent.com\/-EiSjo0bdC-o\/WPS6pkDvdMI\/AAAAAAAAADw\/mKyK9Y8ZQ_MiLrzzq_Spo5VOVA7w2lLoQCLIB\/w714-h306-k-no\/","latitude":"77.15041959999999","name":" Meratask","rating":"5.0","phno":"097179 99666 ","longitude":"28.6909276"},{"website":"pps.in ","address":"Sn 143132, Bank Street, Chapparwal, Near Jain Mandir Naiwala, Karol Bagh Block 44Q, Beadonpura, Karol Bagh New Delhi, Delhi 110005.","reviewsLink":"https:\/\/www.google.com\/search?q=Prakash+Parcel+Services+Limited,+Sn+143132,+Bank+Street,+Chapparwal,+Near+Jain+Mandir,+Naiwala,+Karol+Bagh,+Block+44Q,+Beadonpura,+Karol+Bagh,+New+Delhi,+Delhi+110005&amp;ludocid=10804628454733389149#lrd=0x390d02850b96d631:0x95f1c0558e761d5d,1","reviews":"1 ","img_url":"http:\/\/www.google.com\/earth\/rpc\/images\/cleardot.gif","latitude":"77.191492","name":" Prakash Parcel Services Limited","rating":"5.0","phno":"080 2212 4222 ","longitude":"28.653414"},{"website":"pps.in ","address":"Tilak Bazar Chhota Chamarwara, Khari Baoli, Old Delhi New Delhi, Delhi 110006.","reviewsLink":"#","reviews":"null","img_url":"http:\/\/www.google.com\/earth\/rpc\/images\/cleardot.gif","latitude":"77.2209117","name":" Prakash Parcel Services Ltd","rating":"null","phno":"011 2394 8892 ","longitude":"28.6590571"},{"website":"overnitenet.com ","address":"NO. 117 - B, Kishan Garh Vasant Kunj-Mehrauli Road Masudpur Village, Sector B, Vasant Kunj New Delhi, Delhi 110037.","reviewsLink":"https:\/\/www.google.com\/search?q=Overnite+Express+Courier,+NO.+117+-+B,+Kishan+Garh,+Vasant+Kunj-Mehrauli+Road,+Masudpur+Village,+Sector+B,+Vasant+Kunj,+New+Delhi,+Delhi+110037&amp;ludocid=2291538221673506819#lrd=0x390d1dd5ed81db91:0x1fcd2ddf1c146803,1","reviews":"1 ","img_url":"http:\/\/www.google.com\/earth\/rpc\/images\/cleardot.gif","latitude":"77.15301199999999","name":" Overnite Express Courier","rating":"5.0","phno":"011 2612 5524 ","longitude":"28.526177"},{"website":"pps.in ","address":"Mayapuri Industrial Phase 2nd Road Block A, Mayapuri Industrial Area Phase II, Mayapuri New Delhi, Delhi 110064.","reviewsLink":"#","reviews":"null","img_url":"http:\/\/www.google.com\/earth\/rpc\/images\/cleardot.gif","latitude":"77.126964","name":" Prakash Parcel Services Ltd","rating":"null","phno":"011 3252 4785 ","longitude":"28.630717"},{"website":"pps.in ","address":"Pps-bo-sadar Bazar, No. 105, Qutab Road, Sadar Bazar, Rui Mandi, Sadar Bazaar New Delhi, Delhi 110006.","reviewsLink":"#","reviews":"null","img_url":"http:\/\/www.google.com\/earth\/rpc\/images\/cleardot.gif","latitude":"77.2168935","name":" Prakash Parcel Services Ltd","rating":"null","phno":"011 2361 9474 ","longitude":"28.6587081"},{"website":"pps.in ","address":"Gas Turbine Power Station, IP Estate New Delhi, Delhi 110002.","reviewsLink":"#","reviews":"null","img_url":"http:\/\/www.google.com\/earth\/rpc\/images\/cleardot.gif","latitude":"77.2492","name":" Prakash Parcel Services Ltd","rating":"null","phno":"011 2321 4202 ","longitude":"28.623731"},{"website":"fastwayindia.com ","address":"X-52, 1st Floor, Main Market, West patel Nagar Block 2, East Patel Nagar, Patel Nagar New Delhi, Delhi 110008.","reviewsLink":"https:\/\/www.google.com\/search?q=Fastway+Worldwide+Express,+X-52,+1st+Floor,+Main+Market,+West+patel+Nagar,+Block+2,+East+Patel+Nagar,+Patel+Nagar,+New+Delhi,+Delhi+110008&amp;ludocid=1053401032495574407#lrd=0x390d02f050479a61:0xe9e6ea86bedad87,1","reviews":"2 ","img_url":"http:\/\/www.google.com\/earth\/rpc\/images\/cleardot.gif","latitude":"77.169288","name":" Fastway Worldwide Express","rating":"5.0","phno":"095606 35786 ","longitude":"28.64498099999999"},{"website":"pps.in ","address":"Old Rohtak Rd Phase 3, Shivaji Nagar, Daya Basti New Delhi, Delhi 110052.","reviewsLink":"#","reviews":"null","img_url":"http:\/\/www.google.com\/earth\/rpc\/images\/cleardot.gif","latitude":"77.17385399999999","name":" Prakash Parcel Services Limited","rating":"null","phno":"011 2364 8529 ","longitude":"28.669038"},{"website":"rajdhaniairexpress.com ","address":"Shop No 106 Chaudhary Hukum Chand Marg Humayunpur Village, Humayunpur, Safdarjung Enclave New Delhi, Delhi 110029.","reviewsLink":"https:\/\/www.google.com\/search?q=Rajdhani+Air+Express+PVT.+LTD.,+Shop+No+106,+Chaudhary+Hukum+Chand+Marg,+Humayunpur+Village,+Humayunpur,+Safdarjung+Enclave,+New+Delhi,+Delhi+110029&amp;ludocid=2579309454255899541#lrd=0x390d1d883534647d:0x23cb8c486abac395,1","reviews":"5 ","img_url":"http:\/\/lh3.googleusercontent.com\/-8KzCtm6jDOI\/V6mgXYsXY-I\/AAAAAAAAABc\/C-VqbJ3nssM7f9OmXQP46hod7JzomppKACJkC\/w408-h408-k-no\/","latitude":"77.19328419999999","name":" Rajdhani Air Express PVT. LTD.","rating":"3.4","phno":"011 4615 0182 ","longitude":"28.5608501"},{"website":"pps.in ","address":"Rohtak Rd Mundka Industrial Area, Mundka Delhi, 110081.","reviewsLink":"#","reviews":"null","img_url":"http:\/\/www.google.com\/earth\/rpc\/images\/cleardot.gif","latitude":"76.999827","name":" Prakash Parcel Services Ltd","rating":"null","phno":"093128 32324 ","longitude":"28.681449"},{"website":"overnitenet.com ","address":"11099-C, East Park Road Overnite House Block 18B, Dev Nagar, Karol Bagh New Delhi, Delhi 110005.","reviewsLink":"https:\/\/www.google.com\/search?q=Overnite+Express+Ltd,+11099-C,+East+Park+Road,+Overnite+House,+Block+18B,+Dev+Nagar,+Karol+Bagh,+New+Delhi,+Delhi+110005&amp;ludocid=13834535012586486469#lrd=0x390d0284b83b02e7:0xbffe244ba1ebfac5,1","reviews":"6 ","img_url":"http:\/\/www.google.com\/earth\/rpc\/images\/cleardot.gif","latitude":"77.1874601","name":" Overnite Express Ltd","rating":"1.7","phno":"090150 40000 ","longitude":"28.6556793"},{"website":"balajicourier.com ","address":"Shop No. 1 &amp; 2 Bharat Singh Market, Opposite B-7, Gate No. 1 Vasant Kunj Masudpur Village, Sector B, Vasant Kunj New Delhi, Delhi 110070.","reviewsLink":"https:\/\/www.google.com\/search?q=Balaji+DHL+Courier,+Shop+No.+1+%26+2+Bharat+Singh+Market,+Opposite+B-7,+Gate+No.+1+Vasant+Kunj,+Masudpur+Village,+Sector+B,+Vasant+Kunj,+New+Delhi,+Delhi+110070&amp;ludocid=7086301652922441345#lrd=0x390d1dd615e1a477:0x625799cef9b49e81,1","reviews":"15 ","img_url":"http:\/\/lh4.googleusercontent.com\/-MbI5x2sbmaQ\/Wa4jkr1kvQI\/AAAAAAAEZIk\/k5y3ydgXLYcdajxeXbTR-XaUaxOS_bdMACJkCGAYYCw\/w719-h306-k-no\/","latitude":"77.1556319","name":" Balaji DHL Courier","rating":"4.1","phno":"011 4030 4020 ","longitude":"28.5267803"},{"website":"pps.in ","address":"No.3437,Nicholson Road, Kashmere Gate Ram Bazar, South Indian Madrasi Colony, Mori Gate New Delhi, Delhi 110006.","reviewsLink":"#","reviews":"null","img_url":"http:\/\/www.google.com\/earth\/rpc\/images\/cleardot.gif","latitude":"77.2239113","name":" Prakash Parcel Services Ltd","rating":"null","phno":"011 2397 9078 ","longitude":"28.6650721"},{"website":"bombinoexp.com ","address":"A-38, Local Shopping Complex Shindi Colony, Naraina Village, Naraina New Delhi, Delhi 110028.","reviewsLink":"https:\/\/www.google.com\/search?q=Bombino+Express,+A-38,+Local+Shopping+Complex,+Shindi+Colony,+Naraina+Village,+Naraina,+New+Delhi,+Delhi+110028&amp;ludocid=14115102360743723587#lrd=0x390d033036bdbbf9:0xc3e2eacfe4684243,1","reviews":"4 ","img_url":"http:\/\/www.google.com\/earth\/rpc\/images\/cleardot.gif","latitude":"77.13595529999999","name":" Bombino Express","rating":"3.0","phno":"011 4560 1111 ","longitude":"28.6245534"},{"website":"overnitenet.com ","address":"Shop No. 33, Kashmiri Market, Opposite. Shankar Market Connaught place Hanuman Road Area, Connaught Place New Delhi, Delhi 110001.","reviewsLink":"https:\/\/www.google.com\/search?q=Overnite+Express,+Shop+No.+33,+Kashmiri+Market,+Opposite.+Shankar+Market,+Connaught+place,+Hanuman+Road+Area,+Connaught+Place,+New+Delhi,+Delhi+110001&amp;ludocid=1600806400572942376#lrd=0x390cfd4f90ff7735:0x163734f09c526828,1","reviews":"1 ","img_url":"http:\/\/lh6.googleusercontent.com\/-TK5POJDXrgI\/WTVlzZzDZzI\/AAAAAAAAABU\/T_MSS5lhDec_dOSwp7ry7ejJccY9O5Q6gCLIB\/w544-h306-k-no\/","latitude":"77.216667","name":" Overnite Express","rating":"5.0","phno":"096509 80180 ","longitude":"28.631451"},{"website":" ","address":"B-13, Kirti Nagar Kirti Nagar Block A, Indira Colony, Kirti Nagar New Delhi, Delhi 110015.","reviewsLink":"#","reviews":"null","img_url":"http:\/\/www.google.com\/earth\/rpc\/images\/cleardot.gif","latitude":"77.13761959999999","name":" Express Parcel Services P Ltd","rating":"null","phno":"011 2510 0970 ","longitude":"28.6549351"},{"website":"pps.in ","address":"Kailash Nagar, Gandhi Nagar, Seelampur, Shahdara Delhi, 110031.","reviewsLink":"#","reviews":"null","img_url":"http:\/\/www.google.com\/earth\/rpc\/images\/cleardot.gif","latitude":"77.259192","name":" Prakash Parcel Services Limited","rating":"null","phno":"093122 85302 ","longitude":"28.666375"},{"website":"indiapost.gov.in ","address":"2106, Chah Indara, HC Sen Road, Bhagirath Place Chandni Chowk Bhagirath Palace, Chhippy Wada, Old Delhi New Delhi, Delhi 110006.","reviewsLink":"https:\/\/www.google.com\/search?q=Speed+Post,+2106,+Chah+Indara,+HC+Sen+Road,+Bhagirath+Place,+Chandni+Chowk,+Bhagirath+Palace,+Chhippy+Wada,+Old+Delhi,+New+Delhi,+Delhi+110006&amp;ludocid=12061125248505623845#lrd=0x390cfd1b1edd3dd3:0xa761b982ccac3525,1","reviews":"8 ","img_url":"http:\/\/www.google.com\/earth\/rpc\/images\/cleardot.gif","latitude":"77.23217","name":" Speed Post","rating":"3.6","phno":"099102 20410 ","longitude":"28.657528"},{"website":"gati.com ","address":"C 42 Okhala Estate Marg, Okhla Industrial Area II, Okhla Phase II, Okhla Industrial A Harkesh Nagar, Okhla Industrial Area New Delhi, Delhi 110020.","reviewsLink":"https:\/\/www.google.com\/search?q=Gati+Private+Limited,+C+42,+Okhala+Estate+Marg,+Okhla+Industrial+Area+II,+Okhla+Phase+II,+Okhla+Industrial+A,+Harkesh+Nagar,+Okhla+Industrial+Area,+New+Delhi,+Delhi+110020&amp;ludocid=1557610605889171191#lrd=0x390ce3fd0ac024db:0x159dbe97ee67aef7,1","reviews":"17 ","img_url":"http:\/\/www.google.com\/earth\/rpc\/images\/cleardot.gif","latitude":"77.27508619999999","name":" Gati Private Limited","rating":"2.3","phno":"011 2920 7400 ","longitude":"28.5428977"},{"website":"bluedarttrackings.in ","address":"2\/9, Ground Floor, Sarai Jullena, New Friends Colony Sarai Jullena, New Friends Colony Delhi, 110025.","reviewsLink":"#","reviews":"null","img_url":"http:\/\/lh6.googleusercontent.com\/-ead-rWx86y0\/V2kycjJbJzI\/AAAAAAAAABI\/WcDD4ZfBgDYuRd6eSqU_6Vd2nsto1TIdwCJkC\/w408-h419-k-no\/","latitude":"77.27176399999999","name":" Blue Dart","rating":"null","phno":"093123 30102 ","longitude":"28.560065"},{"website":"bluedart.com ","address":"Indira Gandhi International Airport New Delhi, Delhi 110037.","reviewsLink":"https:\/\/www.google.com\/search?q=Bluedart+Aviation+Delhi,+Indira+Gandhi+International+Airport,+New+Delhi,+Delhi+110037&amp;ludocid=13642767160682005561#lrd=0x390d1c799ac56e65:0xbd54d8733dd0c439,1","reviews":"6 ","img_url":"http:\/\/www.google.com\/earth\/rpc\/images\/cleardot.gif","latitude":"77.10747619999999","name":" Bluedart Aviation Delhi","rating":"3.8","phno":"088600 06415 ","longitude":"28.5577712"},{"website":"dhl.com ","address":"C-97, Ground Floor, Opp. R.P.S. Colony Gate No. 2, M.B. Road, Khanpur Block G, Kailash Colony, Greater Kailash New Delhi, Delhi 110062.","reviewsLink":"https:\/\/www.google.com\/search?q=Bluedart+courier+pvt+ltd,+C-97,+Ground+Floor,+Opp.+R.P.S.+Colony+Gate+No.+2,+M.B.+Road,+Khanpur,+Block+G,+Kailash+Colony,+Greater+Kailash,+New+Delhi,+Delhi+110062&amp;ludocid=13275087024026350676#lrd=0x390ce1a29a43d621:0xb83a95505d7cf454,1","reviews":"2 ","img_url":"http:\/\/lh5.googleusercontent.com\/-RWquFFBRPsg\/Va9PnLa4D4I\/AAAAAAAAAA0\/paumDsQbblw1My7cNZn593Fux8IeaagLQCJkC\/w408-h406-k-no\/","latitude":"77.240398","name":" Bluedart courier pvt ltd","rating":"3.5","phno":"099115 93204 ","longitude":"28.552502"},{"website":"indiapost.gov.in ","address":"g-41 jaina tower-2 district center janakpuri Janakpuri District Center, Janakpuri Delhi, 110058.","reviewsLink":"https:\/\/www.google.com\/search?q=indian+speed+post,+g-41+jaina+tower-2+district+center+janakpuri,+Janakpuri+District+Center,+Janakpuri,+Delhi,+110058&amp;ludocid=1537918161498060235#lrd=0x390d04bf0b9aaaad:0x1557c86b6db6b5cb,1","reviews":"1 ","img_url":"http:\/\/lh3.googleusercontent.com\/-NmPxSPnTr5E\/WK7VUJIKXVI\/AAAAAAAAAAo\/2_j5VXZvY1EFhmKgug8ZPuw9adfivPk7gCLIB\/w661-h306-k-no\/","latitude":"77.08113399999999","name":" indian speed post","rating":"5.0","phno":"011 2554 5169 ","longitude":"28.630048"},{"website":"bluedart.com ","address":"303, Plot No. 4, Pankaj Plaza, 3rd Floor, Sector - 4, Dwarka Pocket 1, Sector 4, Dwarka New Delhi, Delhi 110075.","reviewsLink":"https:\/\/www.google.com\/search?q=Bluedart,+303,+Plot+No.+4,+Pankaj+Plaza,+3rd+Floor,+Sector+-+4,+Dwarka,+Pocket+1,+Sector+4,+Dwarka,+New+Delhi,+Delhi+110075&amp;ludocid=1589474614221528247#lrd=0x390d1ad0cc3abe71:0x160ef2bd802cdcb7,1","reviews":"15 ","img_url":"http:\/\/www.google.com\/earth\/rpc\/images\/cleardot.gif","latitude":"77.0501275","name":" Bluedart","rating":"2.0","phno":"080106 62223 ","longitude":"28.5973395"},{"website":"ups.com ","address":"D-12\/1, Okhla Industrial Area, Phase II Pocket W, Okhla Phase II, Okhla Industrial Area New Delhi, Delhi 110020.","reviewsLink":"https:\/\/www.google.com\/search?q=UPS+Jetair+Express+Pvt.+Ltd.,+D-12\/1,+Okhla+Industrial+Area,+Phase+II,+Pocket+W,+Okhla+Phase+II,+Okhla+Industrial+Area,+New+Delhi,+Delhi+110020&amp;ludocid=190720960757095588#lrd=0x390ce15853b7940f:0x2a593b40d25dca4,1","reviews":"27 ","img_url":"http:\/\/lh4.googleusercontent.com\/-ZOqqd1zOrWA\/WWMt23uJ9oI\/AAAAAAAADLQ\/FGonPpUCNs0iESfGs7zdBgt6aR9AdTZyQCLIBGAYYCw\/w408-h721-k-no\/","latitude":"77.2726215","name":" UPS Jetair Express Pvt. Ltd.","rating":"3.9","phno":"011 7172 6200 ","longitude":"28.5342292"},{"website":"overnitenet.com ","address":"18\/A1, New Rohtak Road Karol Bagh Block 57, Karol Bagh New Delhi, Delhi 110005.","reviewsLink":"#","reviews":"null","img_url":"http:\/\/www.google.com\/earth\/rpc\/images\/cleardot.gif","latitude":"77.1998823","name":" Overnite Business Support Services Private Limited","rating":"null","phno":"011 2362 8327 ","longitude":"28.6548717"},{"website":"dhl.com ","address":"Main Rajouri Garden Market, Red Light Crossing Block A, Vishal Enclave, Rajouri Garden New Delhi, Delhi 110027.","reviewsLink":"https:\/\/www.google.com\/search?q=DHL\/Blue+Dart+Booking+Office,+Main+Rajouri+Garden+Market,+Red+Light+Crossing,+Block+A,+Vishal+Enclave,+Rajouri+Garden,+New+Delhi,+Delhi+110027&amp;ludocid=1296802063397800886#lrd=0x390d0372753672dd:0x11ff2a9b1cd1cbb6,1","reviews":"7 ","img_url":"http:\/\/lh4.googleusercontent.com\/-IFkyOSBUHnA\/VrNElhcLbxI\/AAAAAAAAOr4\/qchUvDswPR8gXom7deVRUaGRPVs5bBbxACJkC\/w542-h306-k-no\/","latitude":"77.1212242","name":" DHL\/Blue Dart Booking Office","rating":"3.9","phno":"092130 20524 ","longitude":"28.6487441"},{"website":"dhl.co.in ","address":"Shop No-115, 1st Floor, Plot No. B09 Itl Twin Tower, Netaji Subash Palace, Pitampura Ring Road Netaji Subash Place, Shakurpur Delhi, 110034.","reviewsLink":"https:\/\/www.google.com\/search?q=DHL+Express+(India)+Pvt.+Ltd,+Shop+No-115,+1st+Floor,+Plot+No.+B09,+Itl+Twin+Tower,+Netaji+Subash+Palace,+Pitampura+Ring+Road,+Netaji+Subash+Place,+Shakurpur,+Delhi,+110034&amp;ludocid=7536291335840783963#lrd=0x390d023388107a65:0x6896490a7ca4de5b,1","reviews":"4 ","img_url":"http:\/\/lh6.googleusercontent.com\/-0eftAhTFNK4\/Vm5mLuEBKhI\/AAAAAAAAABU\/0QgeECLv_j4czy3LE3GD-jN3JwBloKJDwCJkC\/w408-h364-k-no\/","latitude":"77.152562","name":" DHL Express (India) Pvt. Ltd","rating":"4.5","phno":"011 6458 2788 ","longitude":"28.691781"},{"website":"vrlgroup.in ","address":"CB - 383\/9, Indira Market, Opposite Maruthi Showroom\/Workshop Ring Road, Naraina Moti Bagh 1, Block F, Moti Bagh New Delhi, Delhi 110028.","reviewsLink":"https:\/\/www.google.com\/search?q=VRL+Logistics,+CB+-+383\/9,+Indira+Market,+Opposite+Maruthi+Showroom\/Workshop,+Ring+Road,+Naraina,+Moti+Bagh+1,+Block+F,+Moti+Bagh,+New+Delhi,+Delhi+110028&amp;ludocid=10153933030559597645#lrd=0x390d1d144b776af9:0x8cea044b1f9c444d,1","reviews":"1 ","img_url":"http:\/\/www.google.com\/earth\/rpc\/images\/cleardot.gif","latitude":"77.17820639999999","name":" VRL Logistics","rating":"5.0","phno":"080507 60001 ","longitude":"28.5840568"},{"website":"gati.com ","address":"Khasra No.-14\/19\/2,, Opposite Heera Public School, Old Delhi, Gurgaon Road, Samalkha Samalkha, Pushpanjali Farms Delhi, 110037.","reviewsLink":"https:\/\/www.google.com\/search?q=GATI+Limited,+Khasra+No.-14\/19\/2,,+Opposite+Heera+Public+School,+Old+Delhi,,+Gurgaon+Road,+Samalkha,+Samalkha,+Pushpanjali+Farms,+Delhi,+110037&amp;ludocid=5249469345180113555#lrd=0x390d0547db5ab7d5:0x48d9dc8e7ac35a93,1","reviews":"1 ","img_url":"http:\/\/www.google.com\/earth\/rpc\/images\/cleardot.gif","latitude":"77.0883377","name":" GATI Limited","rating":"5.0","phno":"1860 123 4284 ","longitude":"28.5322871"},{"website":"ups.com ","address":"411 Plot 87\/88, Abadi Mahipalur Extension, Mahipalpur Mahipalpur Extension, Mahipalpur New Delhi, Delhi 110037.","reviewsLink":"https:\/\/www.google.com\/search?q=Ups+Jetair+Express+Pvt+Ltd,+411+Plot+87\/88,+Abadi+Mahipalur+Extension,+Mahipalpur,+Mahipalpur+Extension,+Mahipalpur,+New+Delhi,+Delhi+110037&amp;ludocid=16766583069747265079#lrd=0x390d1c3f9e96b4e7:0xe8aede78015d3e37,1","reviews":"3 ","img_url":"http:\/\/www.google.com\/earth\/rpc\/images\/cleardot.gif","latitude":"77.1281345","name":" Ups Jetair Express Pvt Ltd","rating":"3.7","phno":"096220 20020 ","longitude":"28.5448686"},{"website":"bluedart.com ","address":"Shop No. 29, 30 &amp; 31, D-Mall Shopping Complex, Paschim Vihar Sunder Vihar, Paschim Vihar New Delhi, Delhi 110063.","reviewsLink":"https:\/\/www.google.com\/search?q=Blue+Dart,+Shop+No.+29,+30+%26+31,+D-Mall+Shopping+Complex,+Paschim+Vihar,+Sunder+Vihar,+Paschim+Vihar,+New+Delhi,+Delhi+110063&amp;ludocid=2255200115470060806#lrd=0x390d047ab5971883:0x1f4c148e74034d06,1","reviews":"56 ","img_url":"http:\/\/www.google.com\/earth\/rpc\/images\/cleardot.gif","latitude":"77.09152279999999","name":" Blue Dart","rating":"1.9","phno":"1860 233 1234 ","longitude":"28.6668212"},{"website":"kamdhenuairservice.com ","address":"3934\/1, 1st Floor, Om Mkt, Behind 41, G.B.Road, Ajmeri Gate, Fasil Rd Lal Kuan Bazar, Ajmeri Gate New Delhi, Delhi 110006.","reviewsLink":"https:\/\/www.google.com\/search?q=KAMDHENU+AIR+SERVICE,+3934\/1,+1st+Floor,+Om+Mkt,+Behind+41,+G.B.Road,+Ajmeri+Gate,+Fasil+Rd,+Lal+Kuan+Bazar,+Ajmeri+Gate,+New+Delhi,+Delhi+110006&amp;ludocid=2950367374470284611#lrd=0x390cfd309eebed77:0x28f1cf7ed0340543,1","reviews":"6 ","img_url":"http:\/\/lh4.googleusercontent.com\/-dvreF6vt8Sw\/Vk3ESAGhWiI\/AAAAAAAAAGU\/RGhPELYIcj8sFELW7CmrInOQdGbEsOWnwCJkC\/w678-h306-k-no\/","latitude":"77.223315","name":" KAMDHENU AIR SERVICE","rating":"4.5","phno":"011 2321 1796 ","longitude":"28.647508"},{"website":"overnitenet.com ","address":"48\/4, Community Centre Block D, D Block, East of Kailash New Delhi, Delhi 110065.","reviewsLink":"#","reviews":"null","img_url":"http:\/\/www.google.com\/earth\/rpc\/images\/cleardot.gif","latitude":"77.24605699999999","name":" Overnite Express","rating":"null","phno":"093508 99816 ","longitude":"28.557789"},{"website":"indiapost.gov.in ","address":"shop 10, DDA Market, CSC No 3, Pocket D14, Sector 3, Rohini Delhi, 110085.","reviewsLink":"#","reviews":"null","img_url":"http:\/\/lh3.googleusercontent.com\/-SUbQXQlP74M\/Vpeoj1s2foI\/AAAAAAAAABA\/saGrcMcarjAnI0AoY5tqNEGNpY8770VKwCJkC\/w408-h406-k-no\/","latitude":"77.11045399999999","name":" India Post FO","rating":"null","phno":"098733 77500 ","longitude":"28.704898"},{"website":"bluedart.com ","address":"Jhilmil Industrial Area, Jhilmil Colony Industrial Area, Jhilmil Colony Delhi, 110095.","reviewsLink":"https:\/\/www.google.com\/search?q=Blue+Dart,+Jhilmil+Industrial+Area,+Jhilmil+Colony+Industrial+Area,+Jhilmil+Colony,+Delhi,+110095&amp;ludocid=9550557964833809793#lrd=0x390cfb752f3ec419:0x848a65de34b26581,1","reviews":"61 ","img_url":"http:\/\/lh3.googleusercontent.com\/-UzsGy30Q4jY\/WV0ML9VrLwI\/AAAAAAAAFuo\/LNPAhky_dAgToW5r_SXUMBMBWn9inM6_gCLIBGAYYCw\/w544-h306-k-no\/","latitude":"77.3088295","name":" Blue Dart","rating":"1.9","phno":"1860 233 1234 ","longitude":"28.6754996"},{"website":"vrlgroup.in ","address":"40, Ground Floor, Rani Jhansi Road, Opposite To Jhandewalan Mata Mandir Jhandewalan Devi Mandir Marg, Sadar Bazaar, Central Delhi Block A, Motia Khan, Sadar Bazaar New Delhi, Delhi 110055.","reviewsLink":"https:\/\/www.google.com\/search?q=VRL+Logistics,+40,+Ground+Floor,+Rani+Jhansi+Road,+Opposite+To+Jhandewalan+Mata+Mandir,+Jhandewalan+Devi+Mandir+Marg,+Sadar+Bazaar,+Central+Delhi,+Block+A,+Motia+Khan,+Sadar+Bazaar,+New+Delhi,+Delhi+110055&amp;ludocid=8465018090655849100#lrd=0x390cfd4207d00651:0x7579c91a96cc1a8c,1","reviews":"1 ","img_url":"http:\/\/www.google.com\/earth\/rpc\/images\/cleardot.gif","latitude":"77.2053634","name":" VRL Logistics","rating":"5.0","phno":"011 2363 4031 ","longitude":"28.6503539"},{"website":"gati.com ","address":"Centre for Management Studies Road Ghaffar Manzil Colony, Jamia Nagar, Okhla New Delhi, Delhi 110025.","reviewsLink":"https:\/\/www.google.com\/search?q=Mota+Express+Transport,+Centre+for+Management+Studies+Road,+Ghaffar+Manzil+Colony,+Jamia+Nagar,+Okhla,+New+Delhi,+Delhi+110025&amp;ludocid=18031506332223008250#lrd=0x390ce3f4af378957:0xfa3cc779615bedfa,1","reviews":"2 ","img_url":"http:\/\/geo2.ggpht.com\/cbk?panoid=FTZKevFKN7D1Qed7Kg3KQQ&amp;output=thumbnail&amp;cb_client=search.TACTILE.gps&amp;thumb=2&amp;w=408&amp;h=306&amp;yaw=284.81625&amp;pitch=0&amp;thumbfov=100","latitude":"77.281145","name":" Mota Express Transport","rating":"5.0","phno":"098910 90629 ","longitude":"28.5599756"},{"website":"dhl.co.in ","address":"389, Masjid Moth Ndseii Police Colony, South Extension II New Delhi, Delhi 110049.","reviewsLink":"https:\/\/www.google.com\/search?q=DHL,+389,+Masjid+Moth+Ndseii,+Police+Colony,+South+Extension+II,+New+Delhi,+Delhi+110049&amp;ludocid=1431337461078061444#lrd=0x390ce2425aaaaaab:0x13dd21d659447184,1","reviews":"3 ","img_url":"http:\/\/www.google.com\/earth\/rpc\/images\/cleardot.gif","latitude":"77.22023899999999","name":" DHL","rating":"3.7","phno":"098993 90847 ","longitude":"28.561531"},{"website":"indiapost.gov.in ","address":"Near ITM University Old Delhi Rd Sector 23 Pocket F, Dundahera Village, Palam Vihar Gurugram, Haryana 122016.","reviewsLink":"https:\/\/www.google.com\/search?q=India+Post,+Near+ITM+University+Old+Delhi+Rd+Sector+23,+Pocket+F,+Dundahera+Village,+Palam+Vihar,+Gurugram,+Haryana+122016&amp;ludocid=5124610474713050745#lrd=0x390d195e04f404b3:0x471e46134d846e79,1","reviews":"11 ","img_url":"http:\/\/www.google.com\/earth\/rpc\/images\/cleardot.gif","latitude":"77.03689249999999","name":" India Post","rating":"2.5","phno":"098107 07481 ","longitude":"28.5127828"},{"website":"ups.com ","address":"1075\/1, Old Post Office Building 1st Floor Mehrauli Jawahar Lal Nehru University, Old JNU Campus, Munirka New Delhi, Delhi 110030.","reviewsLink":"#","reviews":"null","img_url":"http:\/\/www.google.com\/earth\/rpc\/images\/cleardot.gif","latitude":"77.179402","name":" Ups Courier","rating":"null","phno":"1800 11 2011 ","longitude":"28.550818"},{"website":"dhl.co.in ","address":"Shop No 2, G-7 Gaurav Appartment New Delhi, Block D, Saket New Delhi, Delhi 110017.","reviewsLink":"https:\/\/www.google.com\/search?q=DHL+Express+(India)+Pvt.+Ltd,+Shop+No+2,+G-7+Gaurav+Appartment+New+Delhi,,+Block+D,+Saket,+New+Delhi,+Delhi+110017&amp;ludocid=16868440870020966239#lrd=0x390ce1f77dc4d5d1:0xea18bd993447e75f,1","reviews":"20 ","img_url":"http:\/\/lh4.googleusercontent.com\/-G14UBuDI6A4\/WPidfCpuo5I\/AAAAAAAAD7w\/F2AXPznz_s8D9YH-z8eHJ5QcAisUhi_uACLIB\/w408-h716-k-no\/","latitude":"77.2061483","name":" DHL Express (India) Pvt. Ltd","rating":"4.8","phno":"011 2656 1297 ","longitude":"28.5272434"},{"website":"vrlgroup.in ","address":"DELHIPLOT NO.42 KHASRA NO.39\/7 TEACHERS COLONY SAMAIPUR Badli, Saroop Nagar, Bhalswa Delhi, 110042.","reviewsLink":"https:\/\/www.google.com\/search?q=VRL+logistics,+DELHIPLOT+NO.42+KHASRA+NO.39\/7+TEACHERS+COLONY+SAMAIPUR,+Badli,+Saroop+Nagar,+Bhalswa,+Delhi,+110042&amp;ludocid=7045206777965057943#lrd=0x390d010514f41a85:0x61c59a3cc9c81797,1","reviews":"3 ","img_url":"http:\/\/www.google.com\/earth\/rpc\/images\/cleardot.gif","latitude":"77.14137459999999","name":" VRL logistics","rating":"3.0","phno":"096438 20761 ","longitude":"28.7436659"},{"website":" ","address":"Shop No 17, Khanna Market, 2nd Floor, Tis Hazari Khanna Market Block BGS, Railway Colony, Tis Hazari New Delhi, Delhi 110054.","reviewsLink":"#","reviews":"null","img_url":"http:\/\/www.google.com\/earth\/rpc\/images\/cleardot.gif","latitude":"77.21680359999999","name":" Ganpati Parcel Service","rating":"null","phno":"011 2383 2035 ","longitude":"28.6655972"},{"website":"overnitenet.com ","address":"B-9\/59 Sector 3 Pocket 9, Sector 3B, Rohini Delhi 110085.","reviewsLink":"https:\/\/www.google.com\/search?q=Overnite+Express+Limited,+B-9\/59,+Sector+3,+Pocket+9,+Sector+3B,+Rohini,+Delhi+110085&amp;ludocid=12505959166886802107#lrd=0x390d03fdecd30687:0xad8e179a55d3f2bb,1","reviews":"6 ","img_url":"http:\/\/lh6.googleusercontent.com\/-JzmBLhZgC3g\/V71BmKpHGUI\/AAAAAAAAABE\/CcRJLSNJrRUhAX6RicQsJu6h7ERVvS3nQCJkC\/w408-h408-k-no\/","latitude":"77.109753","name":" Overnite Express Limited","rating":"1.7","phno":"011 4552 1230 ","longitude":"28.703887"},{"website":" ","address":"Plot No. 563, Palam Vihar Road, Near Golok Dham Temple, Bijwasan Dalmia Vihar, Bijwasan New Delhi, Delhi 110061.","reviewsLink":"https:\/\/www.google.com\/search?q=Aramex+-+Delhi,+Plot+No.+563,+Palam+Vihar+Road,+Near+Golok+Dham+Temple,+Bijwasan,+Dalmia+Vihar,+Bijwasan,+New+Delhi,+Delhi+110061&amp;ludocid=6922290503034634400#lrd=0x390d1bcb6ee30cd9:0x6010ea89617080a0,1","reviews":"9 ","img_url":"http:\/\/www.google.com\/earth\/rpc\/images\/cleardot.gif","latitude":"77.05837099999999","name":" Aramex Delhi","rating":"2.6","phno":"011 3090 0450 ","longitude":"28.534474"},{"website":" ","address":"G2, Rajdhani Plaza, LSC, Vikas Marg New Rajdhani Enclave, Swasthya Vihar Delhi, 110092.","reviewsLink":"https:\/\/www.google.com\/search?q=Aramex+-+New+Delhi,+G2,+Rajdhani+Plaza,+LSC,+Vikas+Marg,+New+Rajdhani+Enclave,+Swasthya+Vihar,+Delhi,+110092&amp;ludocid=6744500647804404190#lrd=0x390cfb5a9d32488b:0x5d99479af3c601de,1","reviews":"1 ","img_url":"http:\/\/www.google.com\/earth\/rpc\/images\/cleardot.gif","latitude":"77.29584","name":" Aramex New Delhi","rating":"5.0","phno":"098185 84080 ","longitude":"28.642424"},{"website":"aramex.com ","address":"A15, Mayapuri Industrial Area, Phase 2, Mayapuri Mayapuri Industrial Area Phase II, Mayapuri New Delhi, Delhi 110064.","reviewsLink":"https:\/\/www.google.com\/search?q=Aramex+-+Mayapuri,+A15,+Mayapuri+Industrial+Area,+Phase+2,+Mayapuri,+Mayapuri+Industrial+Area+Phase+II,+Mayapuri,+New+Delhi,+Delhi+110064&amp;ludocid=10919540811343823833#lrd=0x390d034d365d917b:0x978a0083828783d9,1","reviews":"14 ","img_url":"http:\/\/www.google.com\/earth\/rpc\/images\/cleardot.gif","latitude":"77.11558699999999","name":" Aramex Mayapuri","rating":"3.1","phno":"null","longitude":"28.614067"},{"website":"bluedarttracking.in ","address":"Shop No. 157, Vardhman Plus City Mall Road Number 226 Sector 23, Dwarka New Delhi, Delhi 110075.","reviewsLink":"https:\/\/www.google.com\/search?q=Blue+Dart,+Shop+No.+157,+Vardhman+Plus+City+Mall,+Road+Number+226,+Sector+23,+Dwarka,+New+Delhi,+Delhi+110075&amp;ludocid=12866565744834078295#lrd=0x390d1affc1b3c3a1:0xb28f395ffc0b6657,1","reviews":"12 ","img_url":"http:\/\/www.google.com\/earth\/rpc\/images\/cleardot.gif","latitude":"77.055206","name":" Blue Dart","rating":"2.0","phno":"088001 79745 ","longitude":"28.563481"},{"website":"bluedart.com ","address":"Mayur Place, Trilokpuri Mayur Place, Mayur Vihar Phase 1 New Delhi, Delhi 110091.","reviewsLink":"https:\/\/www.google.com\/search?q=BLUE+DART,+Mayur+Place,+Trilokpuri,+Mayur+Place,+Mayur+Vihar+Phase+1,+New+Delhi,+Delhi+110091&amp;ludocid=13197845698608813961#lrd=0x390ce48591154353:0xb7282abcd9fed789,1","reviews":"20 ","img_url":"http:\/\/www.google.com\/earth\/rpc\/images\/cleardot.gif","latitude":"77.2966263","name":" BLUE DART","rating":"2.4","phno":"1860 233 1234 ","longitude":"28.5919572"},{"website":"dhl.com ","address":"144\/A, Maharani Bagh Taimoor Nagar Block D, Maharani Bagh, New Friends Colony New Delhi, Delhi 110025.","reviewsLink":"https:\/\/www.google.com\/search?q=DHL+International,+144\/A,+Maharani+Bagh,+Taimoor+Nagar,+Block+D,+Maharani+Bagh,+New+Friends+Colony,+New+Delhi,+Delhi+110025&amp;ludocid=5137978087876978059#lrd=0x390ce3a29d89b631:0x474dc3d947a5e58b,1","reviews":"5 ","img_url":"http:\/\/www.google.com\/earth\/rpc\/images\/cleardot.gif","latitude":"77.263498","name":" DHL International","rating":"2.4","phno":"011 2692 0148 ","longitude":"28.572311"},{"website":"ups.com ","address":"Delhi - Jaipur Expy DLF Cyber City, DLF Phase 2, Sector 25 Gurugram, Haryana 122002.","reviewsLink":"https:\/\/www.google.com\/search?q=UPS+Courier+Gurgaon,+Delhi+-+Jaipur+Expy,+DLF+Cyber+City,+DLF+Phase+2,+Sector+25,+Gurugram,+Haryana+122002&amp;ludocid=16097512725271353622#lrd=0x390d1947c63887ed:0xdf65da890d211916,1","reviews":"4 ","img_url":"http:\/\/www.google.com\/earth\/rpc\/images\/cleardot.gif","latitude":"77.0897784","name":" UPS Courier Gurgaon","rating":"4.8","phno":"099589 01307 ","longitude":"28.4984973"},{"website":"dhl.com ","address":"384 A Janta Flats Pocket -N Sarita Vihar Madanpur Khadar Village, Madanpur Khadar New Delhi, Delhi 110076.","reviewsLink":"#","reviews":"null","img_url":"http:\/\/www.google.com\/earth\/rpc\/images\/cleardot.gif","latitude":"77.29757699999999","name":" DHL INTERNATIONAL","rating":"null","phno":"093110 62323 ","longitude":"28.536613"},{"website":"dtdc.in ","address":"B1\/12, Building No. 95, Vishal Bhawan, Near Modi Tower Nehru Place Market Nehru Place New Delhi, Delhi 110019.","reviewsLink":"https:\/\/www.google.com\/search?q=Domestic+Courier+Services,+B1\/12,+Building+No.+95,+Vishal+Bhawan,+Near+Modi+Tower,+Nehru+Place+Market,+Nehru+Place,+New+Delhi,+Delhi+110019&amp;ludocid=17362452425210608750#lrd=0x390ce3cfe91504eb:0xf0f3d27d924c3c6e,1","reviews":"5 ","img_url":"http:\/\/www.google.com\/earth\/rpc\/images\/cleardot.gif","latitude":"77.2522974","name":" Domestic Courier Services","rating":"3.2","phno":"011 3082 1345 ","longitude":"28.5481358"},{"website":"gatikwe.com ","address":"Khasra No.-14\/19\/2, Opposite Heera Public School, Old Delhi Gurgaon Road, Samalkha Patel Garden, Block B, Sector 15 Dwarka, Dwarka Delhi, 110037.","reviewsLink":"https:\/\/www.google.com\/search?q=GATI+Limited,+Khasra+No.-14\/19\/2,+Opposite+Heera+Public+School,+Old+Delhi,+Gurgaon+Road,+Samalkha,+Patel+Garden,+Block+B,+Sector+15+Dwarka,+Dwarka,+Delhi,+110037&amp;ludocid=8092410181969264219#lrd=0x390d0547db5ab7d5:0x704e042f61083e5b,1","reviews":"4 ","img_url":"http:\/\/lh6.googleusercontent.com\/-yR4AO9Q6v1I\/WUt-3gza49I\/AAAAAAAAAEU\/yIYUY_S58oAJ7_zCAqcU1J82Y8c4CupfwCLIBGAYYCw\/w458-h306-k-no\/","latitude":"77.03157569999999","name":" GATI Limited","rating":"4.5","phno":"011 6653 0700 ","longitude":"28.61764"},{"website":"gatikwe.com ","address":"GC-49, Pul Pehladpur Block E, Molar band Extension, Badarpur New Delhi, Delhi 110044.","reviewsLink":"https:\/\/www.google.com\/search?q=Gati+Kwe,+GC-49,+Pul+Pehladpur,+Block+E,+Molar+band+Extension,+Badarpur,+New+Delhi,+Delhi+110044&amp;ludocid=41315081115826692#lrd=0x390ce71edb5f8775:0x92c7d8edc67a04,1","reviews":"1 ","img_url":"http:\/\/lh4.googleusercontent.com\/-dHX0im-LYMM\/WSkyusq6LuI\/AAAAAAAAAA4\/YClvzWur9zkHrkg84xCLZ2OATrq63u8IwCLIB\/w408-h407-k-no\/","latitude":"77.31297699999999","name":" Gati Kwe","rating":"5.0","phno":"088268 62726 ","longitude":"28.490074"},{"website":"andhracargoservice.com ","address":"343, Kucha Ghasi Ram, Chandni Chowk Chandni Chowk Old Delhi New Delhi, Delhi 110006.","reviewsLink":"https:\/\/www.google.com\/search?q=Andhra+Cargo+Service,+343,+Kucha+Ghasi+Ram,+Chandni+Chowk,+Chandni+Chowk,+Old+Delhi,+New+Delhi,+Delhi+110006&amp;ludocid=5230448979417138432#lrd=0x390cfd1a88feaca1:0x489649a279f68500,1","reviews":"1 ","img_url":"http:\/\/www.google.com\/earth\/rpc\/images\/cleardot.gif","latitude":"77.231","name":" Andhra Cargo Service","rating":"5.0","phno":"null","longitude":"28.656"},{"website":"madhurcouriers.in ","address":"C-95, Monga Complex Ganesh Nagar, Tilak Nagar New Delhi, Delhi 110018.","reviewsLink":"#","reviews":"null","img_url":"http:\/\/lh5.googleusercontent.com\/-iQeEMB86Hzw\/VXpD1L4GnKI\/AAAAAAAAAA0\/QQNC2labzpcnf48QKYKyy9rgxitRX1_5wCJkC\/w408-h408-k-no\/","latitude":"77.08820399999999","name":" Madhur Courier Services","rating":"null","phno":"093127 84143 ","longitude":"28.635427"},{"website":"vrlgroup.in ","address":"SHED NO-2,Central Ware House ,near DSIIDC complex Kirti Nagar Block A, Kirti Nagar Industrial Area, Kirti Nagar New Delhi, Delhi 110015.","reviewsLink":"https:\/\/www.google.com\/search?q=VRL+Logistics+-+Kirtinagar,+SHED+NO-2,Central+Ware+House+,near+DSIIDC+complex,+Kirti+Nagar,+Block+A,+Kirti+Nagar+Industrial+Area,+Kirti+Nagar,+New+Delhi,+Delhi+110015&amp;ludocid=8851944916038352154#lrd=0x390d03030000003b:0x7ad86d0063ca7d1a,1","reviews":"36 ","img_url":"http:\/\/lh5.googleusercontent.com\/-Pnf6VRZFueg\/V49GQGYn9-I\/AAAAAAAAAJQ\/ahf-KKDGb7QkSCUhzHUl2qKLoK_IF56JQCJkC\/w408-h306-k-no\/","latitude":"77.13864679999999","name":" VRL Logistics Kirtinagar","rating":"3.3","phno":"093129 21836 ","longitude":"28.6425021"},{"website":"madhurexpress.net ","address":"29\/97, Gali No 10, Vishwas Nagar Vishwas Nagar Block 30, Vishwas Nagar, Shahdara Delhi, 110032.","reviewsLink":"https:\/\/www.google.com\/search?q=Madhur+Courier+Services,+29\/97,+Gali+No+10,+Vishwas+Nagar,+Vishwas+Nagar,+Block+30,+Vishwas+Nagar,+Shahdara,+Delhi,+110032&amp;ludocid=3266976274166127941#lrd=0x390cfb635cddaad1:0x2d56a19cb74d1d45,1","reviews":"4 ","img_url":"http:\/\/lh6.googleusercontent.com\/-JwmPYL3pw7w\/VXpJA6p0xNI\/AAAAAAAAAB0\/qRKjQDXtz9YA06QVj0XI4KwWo1eZbUTugCJkC\/w522-h306-k-no\/","latitude":"77.29159369999999","name":" Madhur Courier Services","rating":"3.0","phno":"011 2239 1206 ","longitude":"28.6636127"},{"website":"overnitenet.com ","address":"Harsh Vihar, Pitampura Delhi, 110034.","reviewsLink":"#","reviews":"null","img_url":"http:\/\/www.google.com\/earth\/rpc\/images\/cleardot.gif","latitude":"77.128379","name":" Overnite Express Limited","rating":"null","phno":"093130 93656 ","longitude":"28.69993599999999"},{"website":"flymyparcel.com ","address":"Shop No 155, Central Arcade DLF Phase II, MG Road DLF Phase 2, Sector 25 Gurugram, Haryana 122002.","reviewsLink":"#","reviews":"null","img_url":"http:\/\/lh3.googleusercontent.com\/proxy\/jV6fh88TIrfhesaGCYhgtRYkayXiOyoSGCFG3kovsOSWDsjtNXECNHN8w96xftxFLjxEsg7C4y_ZynAFnmhw3EDmPcT3iVIRjEjDAu8LP_NrZfAxcOWrm35DYwvdYbgvk_E1qSsvjethXXoYhR5E8ZDWhg=w543-h306-k-no","latitude":"77.0857384","name":" Fly My Parcel (Online Courier Cargo)","rating":"null","phno":"0124 403 4789 ","longitude":"28.4810332"},{"website":"shatabdiairexpress.com ","address":"S.No:L-203, Veer Savakar Block Vikas Marg, Dayanand Colony Lalita Park, Laxmi Nagar New Delhi, Delhi 110092.","reviewsLink":"https:\/\/www.google.com\/search?q=Shatabdi+Courier+Service,+S.No:L-203,+Veer+Savakar+Block,+Vikas+Marg,+Dayanand+Colony,+Lalita+Park,+Laxmi+Nagar,+New+Delhi,+Delhi+110092&amp;ludocid=5415735819970320595#lrd=0x390cfcaa028324d3:0x4b288f08d2b098d3,1","reviews":"1 ","img_url":"http:\/\/www.google.com\/earth\/rpc\/images\/cleardot.gif","latitude":"77.27555269999999","name":" Shatabdi Courier Service","rating":"5.0","phno":"098103 18640 ","longitude":"28.6293472"},{"website":"dhl.co.in ","address":"Sector 50 Block East Road, Sector 50 A Block, Sector 50 Noida, Uttar Pradesh 201301.","reviewsLink":"https:\/\/www.google.com\/search?q=DHL+Express,+Sector+50+Block+East+Road,+Sector+50,+A+Block,+Sector+50,+Noida,+Uttar+Pradesh+201301&amp;ludocid=1559593852063444533#lrd=0x390ce679400001cf:0x15a4ca586a1fee35,1","reviews":"14 ","img_url":"http:\/\/lh3.googleusercontent.com\/-M0BEzMqQTcs\/Vapll-pxL-I\/AAAAAAAAAKY\/5m6kXju4_48-zlB07ox5tQIwUarMqfMmgCJkC\/w408-h406-k-no\/","latitude":"77.36877199999999","name":" DHL Express","rating":"4.1","phno":"070420 04559 ","longitude":"28.571932"},{"website":"dtdc.in ","address":"C-7\/13, Near Gurudwara Keshav Puram, Ashok Vihar Delhi, 110035.","reviewsLink":"#","reviews":"null","img_url":"http:\/\/lh3.googleusercontent.com\/-wQ4cadbnZFo\/VbtnSj0tkYI\/AAAAAAAAACI\/YADSsochXFkauyVYraayFtSkhgto5zfdwCJkC\/w408-h430-k-no\/","latitude":"77.1722379","name":" DTDC International","rating":"null","phno":"099103 12815 ","longitude":"28.694069"},{"website":"fedex.co.in ","address":"58, Amrit Nagar, South Extension Part-1 Block 13, Lodi Colony New Delhi, Delhi 110003.","reviewsLink":"https:\/\/www.google.com\/search?q=FedEx,+58,+Amrit+Nagar,+South+Extension+Part-1,+Block+13,+Lodi+Colony,+New+Delhi,+Delhi+110003&amp;ludocid=3755428146454562508#lrd=0x390ce2f4000000e5:0x341df60088ed86cc,1","reviews":"3 ","img_url":"http:\/\/www.google.com\/earth\/rpc\/images\/cleardot.gif","latitude":"77.22327","name":" FedEx","rating":"2.3","phno":"093118 01184 ","longitude":"28.58378"},{"website":"shreetirupaticourier.net ","address":"SHOP NO.135, 1ST FLOOR,DDA COMMUNITY CENTRE,J-BLOCK, OPP.SURYA CONTINENTAL, Rajouri Garden Block J, Rajouri Garden Extension, Rajouri Garden Delhi, 110027.","reviewsLink":"https:\/\/www.google.com\/search?q=Shree+Tirupati+Courier+Service,+SHOP+NO.135,+1ST+FLOOR,DDA+COMMUNITY+CENTRE,J-BLOCK,+OPP.SURYA+CONTINENTAL,,+Rajouri+Garden,+Block+J,+Rajouri+Garden+Extension,+Rajouri+Garden,+Delhi,+110027&amp;ludocid=9405306022763872147#lrd=0x390d0368b4414313:0x82865bff0aaebf93,1","reviews":"2 ","img_url":"http:\/\/lh4.googleusercontent.com\/-fslewkI3YEM\/VKva0W9IOUI\/AAAAAAAAABw\/p_p0KtHSwd4t2DgcWLnngcorTz65z99lQCJkC\/w408-h408-k-no\/","latitude":"77.120319","name":" Shree Tirupati Courier Service","rating":"5.0","phno":"011 4558 9978 ","longitude":"28.638821"},{"website":"shreeanjanicourier.com ","address":"House No.1381, Galli No.21, 2nd Floor Nai Walan, Karol Bagh Block 39E, Nai Walan, Karol Bagh New Delhi, Delhi 110005.","reviewsLink":"https:\/\/www.google.com\/search?q=Shree+Anjani+Courier+Services+Pvt.+Ltd.,+House+No.1381,+Galli+No.21,+2nd+Floor,+Nai+Walan,+Karol+Bagh,+Block+39E,+Nai+Walan,+Karol+Bagh,+New+Delhi,+Delhi+110005&amp;ludocid=3092908462258118331#lrd=0x390cfd61c018bec1:0x2aec37dc07b1debb,1","reviews":"4 ","img_url":"http:\/\/lh6.googleusercontent.com\/-79bjTeKORn0\/V07zUYdB4QI\/AAAAAAAAACc\/zEbAxxF8yXk_5xjuiaN8gC5BSbE7f4Q-wCJkC\/w544-h306-k-no\/","latitude":"77.195877","name":" Shree Anjani Courier Services Pvt. Ltd.","rating":"4.0","phno":"093507 11171 ","longitude":"28.648521"},{"website":"skycomex.com ","address":"Plot No.5, Rangpuri, Next To Hotel Radisson Blu NH 8, Mahipalpur Block R, Mahipalpur Village, Mahipalpur New Delhi, Delhi 110037.","reviewsLink":"https:\/\/www.google.com\/search?q=Skycom,+Plot+No.5,+Rangpuri,+Next+To+Hotel+Radisson+Blu,+NH+8,+Mahipalpur,+Block+R,+Mahipalpur+Village,+Mahipalpur,+New+Delhi,+Delhi+110037&amp;ludocid=5050927569131114708#lrd=0x390d1c136fd08e11:0x46187fdcf84990d4,1","reviews":"1 ","img_url":"http:\/\/lh6.googleusercontent.com\/proxy\/Zpt458QxwDJcp6OyytlC89RvurCJlWf9hcfdMru182cO2f9dMRlsaWXRDu8_R5VV7Qe40wragwYfr-BMhbp4JyMIdt36Epc498n54SvupFin1NjCA3edjDMkjRDV0iE4PjZiAKAUhqMQSCUzZ4EUS7qVXg=w408-h725-k-no","latitude":"77.118894","name":" Skycom","rating":"5.0","phno":"011 6940 0066 ","longitude":"28.543"},{"website":"gatikwe.com ","address":"B37, Novel Enclave, Old Delhi Gurgaon Road Prem Nagar, Sector 13 Gurugram, Haryana 122001.","reviewsLink":"https:\/\/www.google.com\/search?q=GATI+KWE+PVT+LTD,+B37,+Novel+Enclave,+Old+Delhi+Gurgaon+Road,+Prem+Nagar,+Sector+13,+Gurugram,+Haryana+122001&amp;ludocid=12860704715930585442#lrd=0x390d19af7844d16b:0xb27a66ccda3bc962,1","reviews":"5 ","img_url":"http:\/\/www.google.com\/earth\/rpc\/images\/cleardot.gif","latitude":"77.04592679999999","name":" GATI KWE PVT LTD","rating":"3.4","phno":"076666 42001 ","longitude":"28.4805454"},{"website":"jumbocourier.com ","address":"E-205 Block E, Lajpat Nagar I, Lajpat Nagar New Delhi, Delhi 110024.","reviewsLink":"https:\/\/www.google.com\/search?q=Jumbo+Courier+%26+Cargo,+E-205,+Block+E,+Lajpat+Nagar+I,+Lajpat+Nagar,+New+Delhi,+Delhi+110024&amp;ludocid=10639208269823200918#lrd=0x390ce3ac8209b6bb:0x93a60f8d6e35ce96,1","reviews":"6 ","img_url":"http:\/\/www.google.com\/earth\/rpc\/images\/cleardot.gif","latitude":"77.2429721","name":" Jumbo Courier Cargo","rating":"4.8","phno":"098111 88123 ","longitude":"28.5741766"},{"website":"fedex.com ","address":"Satguru Ram Singh Marg Block B, Najafgarh Road Industrial Area Block B, Najafgarh Road Industrial Area New Delhi, Delhi 110008.","reviewsLink":"https:\/\/www.google.com\/search?q=Fedex,+Rama+road,+Satguru+Ram+Singh+Marg,+Block+B,+Najafgarh+Road+Industrial+Area,+Block+B,+Najafgarh+Road+Industrial+Area,+New+Delhi,+Delhi+110008&amp;ludocid=16600516523595108702#lrd=0x390d03aa99198afd:0xe660e1d32ce3915e,1","reviews":"39 ","img_url":"http:\/\/lh4.googleusercontent.com\/-FHMYrKjqqx4\/V0BbdqoHBAI\/AAAAAAAAGBU\/ZTR3LlQ9OkcN38jGH_X3PMG4tJ6YDh8ygCJkC\/w408-h306-k-no\/","latitude":"77.160118","name":" Fedex, Rama road","rating":"2.3","phno":"011 3080 3938 ","longitude":"28.6642342"},{"website":"overnitenet.com ","address":"Road 6 Block RZ, Mahipalpur Village, Mahipalpur Block RZ, Mahipalpur Village, Mahipalpur New Delhi, Delhi 110076.","reviewsLink":"https:\/\/www.google.com\/search?q=Overnite+Express+Limited,+Road+6,+Block+RZ,+Mahipalpur+Village,+Mahipalpur,+Block+RZ,+Mahipalpur+Village,+Mahipalpur,+New+Delhi,+Delhi+110076&amp;ludocid=14356705663385855501#lrd=0x390d1c46b30f4bb3:0xc73d43bc5af3e60d,1","reviews":"11 ","img_url":"http:\/\/www.google.com\/earth\/rpc\/images\/cleardot.gif","latitude":"77.13146089999999","name":" Overnite Express Limited","rating":"1.4","phno":"null","longitude":"28.5511427"},{"website":"madhurcouriers.in ","address":"Shop No. 3462\/14, Khandelwal Market, Near Jammu &amp; Kashmir Bank, Bajrang Bali Street Chawri Bazar Shah Ganj, Old Delhi New Delhi, Delhi 110006.","reviewsLink":"#","reviews":"null","img_url":"http:\/\/www.google.com\/earth\/rpc\/images\/cleardot.gif","latitude":"77.220449","name":" Madhur Courier Services","rating":"null","phno":"011 2321 8862 ","longitude":"28.651428"},{"website":"rajdhaniairexpress.com ","address":"188-189, Sai palza ,shop No. 02 Near Bikaner sweet ,Sant Nagar Garhi, East of Kailash sant nagar, Delhi 110065.","reviewsLink":"#","reviews":"null","img_url":"http:\/\/lh5.googleusercontent.com\/-q0TuaZTyR0s\/V6mam7kwzUI\/AAAAAAAAADM\/W4FpVMPf02IiS78N680d-G-3LtRU0RI6ACJkC\/w408-h406-k-no\/","latitude":"77.24912499999999","name":" Rajdhani Air Express PVT. LTD.","rating":"null","phno":"011 4166 5058 ","longitude":"28.553945"},{"website":"rmscouriers.com ","address":"416, Sant Nagar East Of Kailash, Sant Nagar Garhi, East of Kailash New Delhi, Delhi 110065.","reviewsLink":"https:\/\/www.google.com\/search?q=Rms+Couriers+Pvt+Ltd,+416,+Sant+Nagar,+East+Of+Kailash,+Sant+Nagar,+Garhi,+East+of+Kailash,+New+Delhi,+Delhi+110065&amp;ludocid=11513721686175309328#lrd=0x390ce3c8e5555555:0x9fc8f4df0b30de10,1","reviews":"2 ","img_url":"http:\/\/www.google.com\/earth\/rpc\/images\/cleardot.gif","latitude":"77.2491254","name":" Rms Couriers Pvt Ltd","rating":"3.0","phno":"011 2623 5380 ","longitude":"28.5539451"},{"website":"unitedcouriers.biz ","address":"111, Safderjung Enclave Safdarjung Ansari Nagar West New Delhi, Delhi 110029.","reviewsLink":"https:\/\/www.google.com\/search?q=United+Worldwide+Courier+Private+Limited,+111,+Safderjung+Enclave,+Safdarjung,+Ansari+Nagar+West,+New+Delhi,+Delhi+110029&amp;ludocid=5476942660656167751#lrd=0x390ce27825555555:0x4c020254ef97fb47,1","reviews":"3 ","img_url":"http:\/\/lh3.googleusercontent.com\/-CmPjjPQNh-c\/VidG1Wfe26I\/AAAAAAAAAAg\/A6ftugokUJAO1F-trPco90zhRAvFlXCxwCJkC\/w408-h408-k-no\/","latitude":"77.200324","name":" United Worldwide Courier Private Limited","rating":"5.0","phno":"011 4612 2222 ","longitude":"28.564719"},{"website":"jetccs.net ","address":"Road No..6 Mahipalpur K-Block, Rangpuri New Delhi, Delhi 110039.","reviewsLink":"https:\/\/www.google.com\/search?q=Rajdhani+Rail+Cargo+Services,+Road+No..6,+Mahipalpur,+K-Block,+Rangpuri,+New+Delhi,+Delhi+110039&amp;ludocid=16020584350055275290#lrd=0x390d1c3f9e96b4e7:0xde548c95ef3a1b1a,1","reviews":"3 ","img_url":"http:\/\/lh4.googleusercontent.com\/-2xb-pchxYj4\/VwyNc-Ow0LI\/AAAAAAAAABE\/Pwh7DuPunQsY3OS28tC1rsesj0RrmAlEgCJkC\/w468-h306-k-no\/","latitude":"77.12399409999999","name":" Rajdhani Rail Cargo Services","rating":"4.7","phno":"011 6459 8720 ","longitude":"28.5423888"},{"website":"bluedarttrackings.in ","address":"2\/1, Near Sharma photo state, Sarai Jullena, New Friends Colony Sarai Jullena, New Friends Colony Delhi, 110025.","reviewsLink":"#","reviews":"null","img_url":"http:\/\/lh5.googleusercontent.com\/-bGsRg4dFSJQ\/V2kqwDPL7KI\/AAAAAAAAAA8\/K-HmeV_Bu8YKhSwfmuw6q6B5h9AsGcamACJkC\/w408-h407-k-no\/","latitude":"77.27176399999999","name":" Blue Dart","rating":"null","phno":"098114 09405 ","longitude":"28.560065"},{"website":"bluedart.com ","address":"49, Rani Jhansi Road, Jhandewalan, Paharganj Block E 4, Jhandewalan Extension, Jhandewalan New Delhi, Delhi 110055.","reviewsLink":"https:\/\/www.google.com\/search?q=Blue+Dart,+49,+Rani+Jhansi+Road,+Jhandewalan,+Paharganj,+Block+E+4,+Jhandewalan+Extension,+Jhandewalan,+New+Delhi,+Delhi+110055&amp;ludocid=7307989676798792975#lrd=0x390cfd67f29c47c1:0x656b31e443d0550f,1","reviews":"7 ","img_url":"http:\/\/lh5.googleusercontent.com\/-egBf0xDyalM\/VpyXlqmjLfI\/AAAAAAAAAug\/SbWEKJrZNHEf3XB4YQJDY4YkFpe-uPdPwCJkC\/w408-h544-k-no\/","latitude":"77.20470499999999","name":" Blue Dart","rating":"3.4","phno":"1860 233 1234 ","longitude":"28.645794"},{"website":"globalindiaexpress.com ","address":"L-341, Street No. 1, Near Vijay Bank Mahipalpur Extension Block R, Mahipalpur Village, Mahipalpur New Delhi, Delhi 110037.","reviewsLink":"https:\/\/www.google.com\/search?q=Global+India+Express,+L-341,+Street+No.+1,+Near+Vijay+Bank,+Mahipalpur+Extension,+Block+R,+Mahipalpur+Village,+Mahipalpur,+New+Delhi,+Delhi+110037&amp;ludocid=3646318454911619308#lrd=0x390d1c1375428d95:0x329a5350d2f550ec,1","reviews":"114 ","img_url":"http:\/\/lh5.googleusercontent.com\/-z0e20Ydzu9Q\/WPNMUxkzg7I\/AAAAAAAAAGc\/WXEEXVj65osXUwZWUrY_L1-j9I5klyAtwCLIB\/w409-h306-k-no\/","latitude":"77.118399","name":" Global India Express","rating":"4.5","phno":"098104 97982 ","longitude":"28.542258"},{"website":"marutiair.com ","address":"1010, First Floor, Opposite Hanuman Murthi, Phase Road Karol Bagh Block A, Karol Bagh Delhi, 110005.","reviewsLink":"https:\/\/www.google.com\/search?q=Maruti+Air+Courier,+1010,+First+Floor,+Opposite+Hanuman+Murthi,+Phase+Road,+Karol+Bagh,+Block+A,+Karol+Bagh,+Delhi,+110005&amp;ludocid=1683823758609822241#lrd=0x390cfd63df4be903:0x175e24c9844d3221,1","reviews":"2 ","img_url":"http:\/\/www.google.com\/earth\/rpc\/images\/cleardot.gif","latitude":"77.19849669999999","name":" Maruti Air Courier","rating":"3.0","phno":"011 2875 3097 ","longitude":"28.6503036"},{"website":"patel-india.com ","address":"1391\/91 Nicholson Rd Kashmere Gate New Delhi, Delhi 110006.","reviewsLink":"#","reviews":"null","img_url":"http:\/\/lh4.googleusercontent.com\/-CfwBXPFQNF4\/V76v6kWr-6I\/AAAAAAAAAA4\/0zUSr-mjwCgJEMI6sXc_iP9gAkv06jkmgCJkC\/w408-h408-k-no\/","latitude":"77.22823339999999","name":" Patel Roadways","rating":"null","phno":"098917 59686 ","longitude":"28.6659043"},{"website":"skyking.co ","address":"31, Chawri Bazar Road Main Road Manohar Market, Hauz Qazi, Old Delhi New Delhi, Delhi 110006.","reviewsLink":"https:\/\/www.google.com\/search?q=Sky+King+Courier,+31,+Chawri+Bazar+Road,+Main+Road,+Manohar+Market,+Hauz+Qazi,+Old+Delhi,+New+Delhi,+Delhi+110006&amp;ludocid=17117757690155396191#lrd=0x390cfd182c800b47:0xed8e7dece8ec6c5f,1","reviews":"2 ","img_url":"http:\/\/www.google.com\/earth\/rpc\/images\/cleardot.gif","latitude":"77.2294611","name":" Sky King Courier","rating":"3.0","phno":"098999 42624 ","longitude":"28.6500542"}]}